neptune_experimental/__init__.py
neptune_fetcher/__init__.py
neptune_experimental-0.4.1.dist-info/LICENSE
neptune_experimental-0.4.1.dist-info/METADATA
neptune_experimental-0.4.1.dist-info/WHEEL
neptune_experimental-0.4.1.dist-info/entry_points.txt
neptune_experimental-0.4.1.dist-info/RECORD
