Metadata-Version: 2.3
Name: neptune-experimental
Version: 0.4.1
Summary: Neptune Client Experimental
License: Apache-2.0
Keywords: MLOps,ML Experiment Tracking,ML Model Registry,ML Model Store,ML Metadata Store
Author: neptune.ai
Author-email: contact@neptune.ai
Requires-Python: >=3.7,<4.0
Classifier: Development Status :: 4 - Beta
Classifier: Environment :: Console
Classifier: Intended Audience :: Developers
Classifier: Intended Audience :: Science/Research
Classifier: License :: OSI Approved :: Apache Software License
Classifier: Natural Language :: English
Classifier: Operating System :: MacOS
Classifier: Operating System :: Microsoft :: Windows
Classifier: Operating System :: POSIX
Classifier: Operating System :: Unix
Classifier: Programming Language :: Python :: 3
Classifier: Programming Language :: Python :: 3.7
Classifier: Programming Language :: Python :: 3.8
Classifier: Programming Language :: Python :: 3.9
Classifier: Programming Language :: Python :: 3.10
Classifier: Programming Language :: Python :: 3.11
Classifier: Programming Language :: Python :: 3.12
Classifier: Programming Language :: Python :: 3.13
Classifier: Programming Language :: Python :: Implementation :: CPython
Classifier: Topic :: Scientific/Engineering :: Artificial Intelligence
Classifier: Topic :: Software Development :: Libraries :: Python Modules
Requires-Dist: neptune (==1.9.1)
Requires-Dist: tqdm (>=4.66.0)
Requires-Dist: typing_extensions (>=4.0.0,<5.0.0)
Project-URL: Documentation, https://docs.neptune.ai/
Project-URL: Homepage, https://neptune.ai/
Project-URL: Repository, https://github.com/neptune-ai/neptune-client-experimental
Project-URL: Tracker, https://github.com/neptune-ai/neptune-client-experimental/issues
